automappy/__init__.py
automappy/exceptions.py
automappy/mapper.py
automappy/py.typed
automappy/mappers/__init__.py
automappy/mappers/class_mapper.py
automappy/mappers/collection_mapper.py
automappy/mappers/dataclass_mapper.py
automappy/mappers/mapping_mapper.py
automappy/mappers/object_mapper.py
automappy/mappers/primitive_mapper.py
automappy/mappers/registry.py
automappy/types/__init__.py
automappy/types/type_pair.py
automappy-0.1.1.dist-info/METADATA
automappy-0.1.1.dist-info/WHEEL
automappy-0.1.1.dist-info/licenses/LICENSE
automappy-0.1.1.dist-info/RECORD
