Metadata-Version: 2.3
Name: automappy
Version: 0.1.1
Summary: A convention-based object-object mapper in Python.
License-File: LICENSE
Requires-Python: >=3.12
